{"status":"OK","message":"Successfully Get Event Player Stats","data":{"playerPerformanceStats":{"playerID":9609,"playerFirstName":"Jason","playerLastName":"Frady","bucketID":9,"yearDesc":"2023 - 2024","ptsPerRnd":9.43,"rdsTotal":5195,"rounds":5195,"totPtsTotal":48980,"totalPts":48980,"opponentPtsPerRnd":8.98,"OppPtsPerRnd":8.98,"oppPtsTotal":46676,"opponentPts":46676,"DPR":0.45,"diffPerRnd":0.45,"fourBagPct":"28.80","fourBaggerPct":"28.80","bagsInPct":"70.60","BagsInPct":"70.60","bagsOnPct":"23.92","BagsOnPct":"23.92","bagsOffPct":"5.49","BagsOffPct":"5.49"},"playerWinLossStats":{"totalWins":-1},"playerCPIStats":{"playerID":9609,"playerCPI":9.45,"playerMembershipID":0,"CPIQualified":1,"playerMembershipExpiryDate":null,"playerMembershipStatus":"N","playerMembershipType":"N","playerMembershipName":"NO MEMBERSHIP","showPlayerCPI":0}}}