{"status":"OK","message":"Successfully Get Event Player Stats","data":{"playerPerformanceStats":{"playerID":3185,"playerFirstName":"Robbie","playerLastName":"Davis","bucketID":9,"yearDesc":"2023 - 2024","ptsPerRnd":9.44,"rdsTotal":5423,"rounds":5423,"totPtsTotal":51185,"totalPts":51185,"opponentPtsPerRnd":9.1,"OppPtsPerRnd":9.1,"oppPtsTotal":49329,"opponentPts":49329,"DPR":0.34,"diffPerRnd":0.34,"fourBagPct":"29.10","fourBaggerPct":"29.10","bagsInPct":"70.61","BagsInPct":"70.61","bagsOnPct":"24.14","BagsOnPct":"24.14","bagsOffPct":"5.25","BagsOffPct":"5.25"},"playerWinLossStats":{"totalWins":-1},"playerCPIStats":{"playerID":3185,"playerCPI":8.73,"playerMembershipID":0,"CPIQualified":1,"playerMembershipExpiryDate":null,"playerMembershipStatus":"N","playerMembershipType":"N","playerMembershipName":"NO MEMBERSHIP","showPlayerCPI":0}}}