{"status":"OK","message":"Successfully Get Event Player Stats","data":{"playerPerformanceStats":{"playerID":136777,"playerFirstName":"Colin","playerLastName":"Hodet","bucketID":9,"yearDesc":"2023 - 2024","ptsPerRnd":9.44,"rdsTotal":7959,"rounds":7959,"totPtsTotal":75125,"totalPts":75125,"opponentPtsPerRnd":8.65,"OppPtsPerRnd":8.65,"oppPtsTotal":68828,"opponentPts":68828,"DPR":0.79,"diffPerRnd":0.79,"fourBagPct":"30.33","fourBaggerPct":"30.33","bagsInPct":"70.76","BagsInPct":"70.76","bagsOnPct":"23.71","BagsOnPct":"23.71","bagsOffPct":"5.54","BagsOffPct":"5.54"},"playerWinLossStats":{"totalWins":-1},"playerCPIStats":{"playerID":136777,"playerCPI":9.65,"playerMembershipID":0,"CPIQualified":1,"playerMembershipExpiryDate":null,"playerMembershipStatus":"N","playerMembershipType":"N","playerMembershipName":"NO MEMBERSHIP","showPlayerCPI":0}}}